qstatall.py
qstatall-0.1.0.dist-info/licenses/LICENSE
qstatall-0.1.0.dist-info/METADATA
qstatall-0.1.0.dist-info/WHEEL
qstatall-0.1.0.dist-info/entry_points.txt
qstatall-0.1.0.dist-info/top_level.txt
qstatall-0.1.0.dist-info/RECORD
