Metadata-Version: 2.4
Name: qstatall
Version: 0.1.0
Summary: A tool to query and display all SGE job information
Author-email: Liu Yan <liuyanhzau@163.com>
Classifier: Programming Language :: Python :: 3
Classifier: License :: OSI Approved :: MIT License
Classifier: Operating System :: POSIX :: Linux
Requires-Python: >=3.7
License-File: LICENSE
Requires-Dist: tabulate
Dynamic: license-file
